pysatgeo/__init__.py
pysatgeo/download.py
pysatgeo/gee.py
pysatgeo/lidar.py
pysatgeo/netcdf.py
pysatgeo/pysatgeo.py
pysatgeo/raster.py
pysatgeo/vector.py
pysatgeo-0.4.1.dist-info/licenses/LICENSE
pysatgeo-0.4.1.dist-info/METADATA
pysatgeo-0.4.1.dist-info/WHEEL
pysatgeo-0.4.1.dist-info/entry_points.txt
pysatgeo-0.4.1.dist-info/top_level.txt
pysatgeo-0.4.1.dist-info/RECORD
